blockchainbay/blockChainBay.py
blockchainbay/web1.py
blockchainbay/data/static/jquery.js
blockchainbay/data/static/tpb.css
blockchainbay/data/templates/detail.html
blockchainbay/data/templates/index.html
blockchainbay-1.5.5.data/scripts/blockChainBay.py
blockchainbay-1.5.5.dist-info/METADATA
blockchainbay-1.5.5.dist-info/WHEEL
blockchainbay-1.5.5.dist-info/top_level.txt
blockchainbay-1.5.5.dist-info/RECORD
