Metadata-Version: 2.1
Name: blockchainbay
Version: 1.5.5
Summary: The Blockchainbay is a torrent distribution tool hosted on a EVM-compatible blockchain.
Home-page: https://github.com/ortegaalfredo/blockchainbay
Author: Alfredo Ortega
Author-email: ortegaalfredo@gmail.com
Classifier: Programming Language :: Python :: 3
Classifier: License :: OSI Approved :: BSD License
Classifier: Operating System :: OS Independent
Requires-Dist: web3
